{"chunk_definitions":[{"chunk_id":"csetup_chunk","chunk_label":"setup","document_id":"3F647111","expansion_state":0,"options":{"engine":"r","include":false,"label":"setup"},"row":7,"row_count":1,"visible":true},{"chunk_id":"codjs5pvvottk","chunk_label":"unnamed-chunk-67","document_id":"3F647111","expansion_state":0,"options":{"engine":"r","label":"unnamed-chunk-20"},"row":681,"row_count":1,"visible":true},{"chunk_id":"cyttw1coz7xec","chunk_label":"unnamed-chunk-67","document_id":"3F647111","expansion_state":0,"options":{"engine":"r","label":"unnamed-chunk-8"},"row":682,"row_count":1,"visible":true},{"chunk_id":"c48clnx4deke7","chunk_label":"unnamed-chunk-68","document_id":"3F647111","expansion_state":0,"options":{"engine":"r","label":"unnamed-chunk-21"},"row":693,"row_count":1,"visible":true},{"chunk_id":"ctx14ucv5772a","chunk_label":"unnamed-chunk-68","document_id":"3F647111","expansion_state":0,"options":{"engine":"r","label":"unnamed-chunk-9"},"row":694,"row_count":1,"visible":true},{"chunk_id":"cp5wqx4zdistq","chunk_label":"unnamed-chunk-69","document_id":"3F647111","expansion_state":0,"options":{"engine":"r","label":"unnamed-chunk-25"},"row":699,"row_count":1,"visible":true},{"chunk_id":"c6mi47taf0v4q","chunk_label":"unnamed-chunk-69","document_id":"3F647111","expansion_state":0,"options":{"engine":"r","label":"unnamed-chunk-10"},"row":700,"row_count":1,"visible":true},{"chunk_id":"csqd0zt62qf4j","chunk_label":"unnamed-chunk-70","document_id":"3F647111","expansion_state":0,"options":{"engine":"r","label":"unnamed-chunk-11"},"row":703,"row_count":1,"visible":true},{"chunk_id":"c4dwgs68ylvdf","chunk_label":"unnamed-chunk-71","document_id":"3F647111","expansion_state":0,"options":{"engine":"r","label":"unnamed-chunk-28"},"row":706,"row_count":1,"visible":true},{"chunk_id":"cvazh78iz4fso","chunk_label":"unnamed-chunk-71","document_id":"3F647111","expansion_state":0,"options":{"engine":"r","label":"unnamed-chunk-12"},"row":707,"row_count":1,"visible":true},{"chunk_id":"chzqegml3egv0","chunk_label":"unnamed-chunk-72","document_id":"3F647111","expansion_state":0,"options":{"engine":"r","label":"unnamed-chunk-13"},"row":715,"row_count":1,"visible":true},{"chunk_id":"c5i5hg3jrvwhg","chunk_label":"unnamed-chunk-73","document_id":"3F647111","expansion_state":0,"options":{"engine":"r","label":"unnamed-chunk-50"},"row":720,"row_count":1,"visible":true},{"chunk_id":"cjtvsl55zu0un","chunk_label":"unnamed-chunk-73","document_id":"3F647111","expansion_state":0,"options":{"engine":"r","label":"unnamed-chunk-14"},"row":721,"row_count":1,"visible":true},{"chunk_id":"ci6fe5trss9p6","chunk_label":"unnamed-chunk-74","document_id":"3F647111","expansion_state":0,"options":{"engine":"r","label":"unnamed-chunk-15"},"row":725,"row_count":1,"visible":true},{"chunk_id":"czok93tfsmpx5","chunk_label":"unnamed-chunk-75","document_id":"3F647111","expansion_state":0,"options":{"engine":"r","label":"unnamed-chunk-16"},"row":731,"row_count":1,"visible":true},{"chunk_id":"c9fn9ocmtu90g","chunk_label":"unnamed-chunk-76","document_id":"3F647111","expansion_state":0,"options":{"engine":"r","label":"unnamed-chunk-17"},"row":743,"row_count":1,"visible":true},{"chunk_id":"ctv2nak0smzvi","chunk_label":"unnamed-chunk-77","document_id":"3F647111","expansion_state":0,"options":{"engine":"r","label":"unnamed-chunk-18"},"row":753,"row_count":1,"visible":true},{"chunk_id":"cs1lv1tgkzvzf","chunk_label":"unnamed-chunk-78","document_id":"3F647111","expansion_state":0,"options":{"engine":"r","label":"unnamed-chunk-19"},"row":764,"row_count":1,"visible":true},{"chunk_id":"cln1xzucasvud","chunk_label":"unnamed-chunk-79","document_id":"3F647111","expansion_state":0,"options":{"engine":"r","label":"unnamed-chunk-20"},"row":768,"row_count":1,"visible":true},{"chunk_id":"cx5828tz0mpy0","chunk_label":"unnamed-chunk-80","document_id":"3F647111","expansion_state":0,"options":{"engine":"r","label":"unnamed-chunk-21"},"row":774,"row_count":1,"visible":true},{"chunk_id":"cbnxuq25o0u3e","chunk_label":"unnamed-chunk-81","document_id":"3F647111","expansion_state":0,"options":{"engine":"r","label":"unnamed-chunk-22"},"row":783,"row_count":1,"visible":true},{"chunk_id":"cky9umm55cddm","chunk_label":"unnamed-chunk-82","document_id":"3F647111","expansion_state":0,"options":{"engine":"r","label":"unnamed-chunk-23"},"row":786,"row_count":1,"visible":true},{"chunk_id":"c7gnwpv20sjm5","chunk_label":"unnamed-chunk-83","document_id":"3F647111","expansion_state":0,"options":{"engine":"r","label":"unnamed-chunk-24"},"row":797,"row_count":1,"visible":true},{"chunk_id":"cwxkungk5w9jq","chunk_label":"unnamed-chunk-84","document_id":"3F647111","expansion_state":0,"options":{"engine":"r","label":"unnamed-chunk-25"},"row":801,"row_count":1,"visible":true}],"doc_write_time":1588529174}